<eSocial xmlns="http://www.esocial.gov.br/schema/evt/evtAfastTemp/v_S_01_03_00"><evtAfastTemp Id="ID1026679710000002025062012463200000"><ideEvento><indRetif>1</indRetif><tpAmb>1</tpAmb><procEmi>1</procEmi><verProc>12.1.2410.229</verProc></ideEvento><ideEmpregador><tpInsc>1</tpInsc><nrInsc>02667971</nrInsc></ideEmpregador><ideVinculo><cpfTrab>14227198470</cpfTrab><matricula>C03S000668</matricula></ideVinculo><infoAfastamento><iniAfastamento><dtIniAfast>2025-06-20</dtIniAfast><codMotAfast>01</codMotAfast><infoMesmoMtv>N</infoMesmoMtv></iniAfastamento><fimAfastamento><dtTermAfast>2025-06-28</dtTermAfast></fimAfastamento></infoAfastamento></evtAfastTemp></eSocial>